assets/base.css
assets/base2.css
assets/base3.css
assets/dash-financial-logo.png
assets/mssm-logo.png
assets/risk_reward.png
assets/styles.css
biocwl_dash/__init__.py
biocwl_dash/app.py
biocwl_dash/report_service.py
biocwl_dash/utils.py
biocwl_dash/assets/base.css
biocwl_dash/assets/base2.css
biocwl_dash/assets/base3.css
biocwl_dash/assets/dash-financial-logo.png
biocwl_dash/assets/mssm-logo.png
biocwl_dash/assets/risk_reward.png
biocwl_dash/assets/styles.css
biocwl_dash/pages/copyNumberVariation.py
biocwl_dash/pages/expression.py
biocwl_dash/pages/fileBrowser.py
biocwl_dash/pages/geneFusions.py
biocwl_dash/pages/overview.py
biocwl_dash/pages/rabix.py
biocwl_dash/pages/vicc.py
build/lib/biocwl_dash/__init__.py
build/lib/biocwl_dash/app.py
build/lib/biocwl_dash/report_service.py
build/lib/biocwl_dash/utils.py
build/lib/biocwl_dash/pages/copyNumberVariation.py
build/lib/biocwl_dash/pages/expression.py
build/lib/biocwl_dash/pages/fileBrowser.py
build/lib/biocwl_dash/pages/geneFusions.py
build/lib/biocwl_dash/pages/overview.py
build/lib/biocwl_dash/pages/rabix.py
build/lib/biocwl_dash/pages/vicc.py
build/lib/pages/copyNumberVariation.py
build/lib/pages/expression.py
build/lib/pages/fileBrowser.py
build/lib/pages/geneFusions.py
build/lib/pages/overview.py
build/lib/pages/rabix.py
build/lib/pages/vicc.py
build/lib/test/__init__.py
build/lib/test/test_main.py
pages/copyNumberVariation.py
pages/expression.py
pages/fileBrowser.py
pages/geneFusions.py
pages/overview.py
pages/rabix.py
pages/vicc.py
test/__init__.py
test/test_main.py
venv/bin/rst2html.py
venv/bin/rst2html4.py
venv/bin/rst2html5.py
venv/bin/rst2latex.py
venv/bin/rst2man.py
venv/bin/rst2odt.py
venv/bin/rst2odt_prepstyles.py
venv/bin/rst2pseudoxml.py
venv/bin/rst2s5.py
venv/bin/rst2xetex.py
venv/bin/rst2xml.py
venv/bin/rstpep2html.py
biocwl_dash-0.0.6.dist-info/LICENSE
biocwl_dash-0.0.6.dist-info/METADATA
biocwl_dash-0.0.6.dist-info/WHEEL
biocwl_dash-0.0.6.dist-info/top_level.txt
biocwl_dash-0.0.6.dist-info/RECORD
