Metadata-Version: 2.1
Name: biocwl-dash
Version: 0.0.6
Summary: Viewer for Mount Sinai IIDSGT Precision Oncology reports.
Home-page: https://gitlab.com/iidsgt/biocwl-dash
Author: Jacob Roberts
Author-email: jacoberts@gmail.com
License: UNKNOWN
Platform: UNKNOWN
Classifier: Programming Language :: Python :: 3
Classifier: License :: OSI Approved :: MIT License
Classifier: Operating System :: OS Independent
Requires-Python: >=3.6
Requires-Dist: dash
Requires-Dist: flask
Requires-Dist: dash-rabix
Requires-Dist: dash-lazylog
Requires-Dist: pandas
Requires-Dist: pdf2image
Requires-Dist: dash-table
Requires-Dist: pyyaml
Requires-Dist: dash-bio
